{
  "_README": {
    "title": "US Sector Indices - Daily Snapshot (GICS 11 Sectors)",
    "description": "Performance of 11 GICS sectors via Select Sector SPDR ETFs",
    "purpose": "Identify sector rotation, leadership, and relative strength",
    "sectors_explained": {
      "XLK": "Technology - Software, semiconductors, IT services, hardware",
      "XLV": "Health Care - Pharma, biotech, health equipment, providers",
      "XLF": "Financials - Banks, insurance, capital markets, REITs",
      "XLY": "Consumer Discretionary - Retail, automotive, leisure, hotels, restaurants",
      "XLI": "Industrials - Aerospace, defense, machinery, transportation",
      "XLP": "Consumer Staples - Food, beverage, tobacco, household products",
      "XLE": "Energy - Oil, gas, consumable fuels, energy equipment",
      "XLB": "Materials - Chemicals, construction materials, metals, mining",
      "XLC": "Communication Services - Media, entertainment, telecom, interactive media",
      "XLU": "Utilities - Electric, gas, water utilities, renewable energy",
      "XLRE": "Real Estate - REITs, real estate management and development"
    },
    "interpretation": {
      "sector_rotation": "Compare 1-month returns to identify hot sectors",
      "defensive_vs_cyclical": "XLU/XLP outperforming = defensive, XLY/XLK = risk-on",
      "leadership_count": "Count sectors beating S&P 500 for breadth signal",
      "relative_strength": "Sectors at 52-week highs = strongest momentum"
    },
    "pivot_points_usage": {
      "description": "Daily support/resistance levels based on previous day's High, Low, Close",
      "formula": "PP=(H+L+C)/3, R1=(2\u00d7PP)-L, R2=PP+(H-L), R3=H+(2\u00d7(PP-L)), S1=(2\u00d7PP)-H, S2=PP-(H-L), S3=L-(2\u00d7(H-L))",
      "application": "Identify potential reversal points and sector strength thresholds"
    },
    "gics_classification": {
      "10": "Energy (XLE)",
      "15": "Materials (XLB)",
      "20": "Industrials (XLI)",
      "25": "Consumer Discretionary (XLY)",
      "30": "Consumer Staples (XLP)",
      "35": "Health Care (XLV)",
      "40": "Financials (XLF)",
      "45": "Technology (XLK)",
      "50": "Communication Services (XLC)",
      "55": "Utilities (XLU)",
      "60": "Real Estate (XLRE)"
    }
  },
  "metadata": {
    "generated_at": "2025-11-20T15:47:55Z",
    "market_date": "2025-11-20",
    "market_status": "during",
    "indices_count": 11,
    "data_source": "Yahoo Finance (yfinance)",
    "data_quality": {
      "status": "stale",
      "missing_days": 241,
      "completeness_percent": 4.4,
      "last_update": "2025-11-20T15:47:55Z",
      "market_hours": "during"
    }
  },
  "sectors": {
    "XLK": {
      "name": "Technology Select Sector SPDR Fund",
      "symbol": "XLK",
      "sector_name": "Technology",
      "gics_code": "45",
      "description": "Software, semiconductors, IT services, hardware",
      "current_price": 287.28,
      "daily_change": 6.31,
      "daily_change_percent": 2.25,
      "volume": 3920219,
      "day_high": 288.51,
      "day_low": 286.26,
      "day_open": 287.44,
      "52_week_high": 304.13,
      "52_week_low": 179.2,
      "distance_from_52w_high_percent": -5.54,
      "year_to_date_percent": 24.43,
      "1_month_percent": 0.63,
      "3_month_percent": 9.61,
      "6_month_percent": 25.63,
      "relative_to_sp500_1d": 0.43,
      "pivot_points": {
        "pivot_point": 281.14,
        "resistance_1": 283.95,
        "resistance_2": 286.93,
        "resistance_3": 289.74,
        "support_1": 278.16,
        "support_2": 275.35,
        "support_3": 266.75
      }
    },
    "XLV": {
      "name": "Health Care Select Sector SPDR Fund",
      "symbol": "XLV",
      "sector_name": "Health Care",
      "gics_code": "35",
      "description": "Pharma, biotech, health equipment, providers",
      "current_price": 152.34,
      "daily_change": 0.01,
      "daily_change_percent": 0.01,
      "volume": 7029284,
      "day_high": 153.34,
      "day_low": 152.26,
      "day_open": 152.49,
      "52_week_high": 152.82,
      "52_week_low": 127.57,
      "distance_from_52w_high_percent": -0.31,
      "year_to_date_percent": 12.17,
      "1_month_percent": 4.37,
      "3_month_percent": 10.76,
      "6_month_percent": 17.78,
      "relative_to_sp500_1d": -1.81,
      "pivot_points": {
        "pivot_point": 152.28,
        "resistance_1": 152.98,
        "resistance_2": 153.64,
        "resistance_3": 154.34,
        "support_1": 151.62,
        "support_2": 150.92,
        "support_3": 148.85
      }
    },
    "XLF": {
      "name": "Financial Select Sector SPDR Fund",
      "symbol": "XLF",
      "sector_name": "Financials",
      "gics_code": "40",
      "description": "Banks, insurance, capital markets, REITs",
      "current_price": 52.22,
      "daily_change": 0.66,
      "daily_change_percent": 1.28,
      "volume": 15192488,
      "day_high": 52.38,
      "day_low": 51.97,
      "day_open": 52.03,
      "52_week_high": 54.13,
      "52_week_low": 43.63,
      "distance_from_52w_high_percent": -3.52,
      "year_to_date_percent": 9.45,
      "1_month_percent": -0.39,
      "3_month_percent": -2.19,
      "6_month_percent": 4.67,
      "relative_to_sp500_1d": -0.54,
      "pivot_points": {
        "pivot_point": 51.47,
        "resistance_1": 51.74,
        "resistance_2": 51.93,
        "resistance_3": 52.2,
        "support_1": 51.28,
        "support_2": 51.01,
        "support_3": 50.27
      }
    },
    "XLY": {
      "name": "Consumer Discretionary Select Sector SPDR Fund",
      "symbol": "XLY",
      "sector_name": "Consumer Discretionary",
      "gics_code": "25",
      "description": "Retail, automotive, leisure, hotels, restaurants",
      "current_price": 228.95,
      "daily_change": 4.44,
      "daily_change_percent": 1.98,
      "volume": 2207274,
      "day_high": 229.5,
      "day_low": 226.96,
      "day_open": 227.03,
      "52_week_high": 242.18,
      "52_week_low": 175.66,
      "distance_from_52w_high_percent": -5.46,
      "year_to_date_percent": 4.1,
      "1_month_percent": -3.52,
      "3_month_percent": -1.61,
      "6_month_percent": 8.13,
      "relative_to_sp500_1d": 0.16,
      "pivot_points": {
        "pivot_point": 224.69,
        "resistance_1": 226.05,
        "resistance_2": 227.59,
        "resistance_3": 228.95,
        "support_1": 223.15,
        "support_2": 221.79,
        "support_3": 217.53
      }
    },
    "XLI": {
      "name": "Industrial Select Sector SPDR Fund",
      "symbol": "XLI",
      "sector_name": "Industrials",
      "gics_code": "20",
      "description": "Aerospace, defense, machinery, transportation",
      "current_price": 152.13,
      "daily_change": 1.78,
      "daily_change_percent": 1.18,
      "volume": 4266252,
      "day_high": 152.72,
      "day_low": 151.95,
      "day_open": 152.35,
      "52_week_high": 155.79,
      "52_week_low": 115.59,
      "distance_from_52w_high_percent": -2.35,
      "year_to_date_percent": 17.06,
      "1_month_percent": -0.48,
      "3_month_percent": -0.25,
      "6_month_percent": 8.45,
      "relative_to_sp500_1d": -0.64,
      "pivot_points": {
        "pivot_point": 150.27,
        "resistance_1": 150.94,
        "resistance_2": 151.53,
        "resistance_3": 152.2,
        "support_1": 149.68,
        "support_2": 149.01,
        "support_3": 147.08
      }
    },
    "XLP": {
      "name": "Consumer Staples Select Sector SPDR Fund",
      "symbol": "XLP",
      "sector_name": "Consumer Staples",
      "gics_code": "30",
      "description": "Food, beverage, tobacco, household products",
      "current_price": 77.12,
      "daily_change": 0.61,
      "daily_change_percent": 0.8,
      "volume": 6723662,
      "day_high": 77.24,
      "day_low": 76.7,
      "day_open": 76.75,
      "52_week_high": 82.65,
      "52_week_low": 74.8,
      "distance_from_52w_high_percent": -6.69,
      "year_to_date_percent": 0.29,
      "1_month_percent": -3.29,
      "3_month_percent": -5.85,
      "6_month_percent": -3.84,
      "relative_to_sp500_1d": -1.02,
      "pivot_points": {
        "pivot_point": 76.6,
        "resistance_1": 76.98,
        "resistance_2": 77.44,
        "resistance_3": 77.82,
        "support_1": 76.14,
        "support_2": 75.76,
        "support_3": 74.55
      }
    },
    "XLE": {
      "name": "Energy Select Sector SPDR Fund",
      "symbol": "XLE",
      "sector_name": "Energy",
      "gics_code": "10",
      "description": "Oil, gas, consumable fuels, energy equipment",
      "current_price": 91.44,
      "daily_change": 1.56,
      "daily_change_percent": 1.74,
      "volume": 4290239,
      "day_high": 91.44,
      "day_low": 90.13,
      "day_open": 90.34,
      "52_week_high": 94.14,
      "52_week_low": 75.18,
      "distance_from_52w_high_percent": -2.86,
      "year_to_date_percent": 8.12,
      "1_month_percent": 4.15,
      "3_month_percent": 4.64,
      "6_month_percent": 13.76,
      "relative_to_sp500_1d": -0.08,
      "pivot_points": {
        "pivot_point": 89.62,
        "resistance_1": 90.43,
        "resistance_2": 90.97,
        "resistance_3": 91.78,
        "support_1": 89.08,
        "support_2": 88.27,
        "support_3": 86.12
      }
    },
    "XLB": {
      "name": "Materials Select Sector SPDR Fund",
      "symbol": "XLB",
      "sector_name": "Materials",
      "gics_code": "15",
      "description": "Chemicals, construction materials, metals, mining",
      "current_price": 86.49,
      "daily_change": 0.75,
      "daily_change_percent": 0.87,
      "volume": 2154330,
      "day_high": 86.71,
      "day_low": 86.06,
      "day_open": 86.33,
      "52_week_high": 93.2,
      "52_week_low": 73.54,
      "distance_from_52w_high_percent": -7.2,
      "year_to_date_percent": 5.47,
      "1_month_percent": -2.07,
      "3_month_percent": -5.73,
      "6_month_percent": 1.72,
      "relative_to_sp500_1d": -0.95,
      "pivot_points": {
        "pivot_point": 85.68,
        "resistance_1": 86.16,
        "resistance_2": 86.58,
        "resistance_3": 87.06,
        "support_1": 85.26,
        "support_2": 84.78,
        "support_3": 83.4
      }
    },
    "XLC": {
      "name": "Communication Services Select Sector SPDR Fund",
      "symbol": "XLC",
      "sector_name": "Communication Services",
      "gics_code": "50",
      "description": "Media, entertainment, telecom, interactive media",
      "current_price": 112.96,
      "daily_change": 1.77,
      "daily_change_percent": 1.59,
      "volume": 1597056,
      "day_high": 113.04,
      "day_low": 112.32,
      "day_open": 112.8,
      "52_week_high": 119.0,
      "52_week_low": 85.62,
      "distance_from_52w_high_percent": -5.07,
      "year_to_date_percent": 17.16,
      "1_month_percent": -2.31,
      "3_month_percent": 1.84,
      "6_month_percent": 12.9,
      "relative_to_sp500_1d": -0.23,
      "pivot_points": {
        "pivot_point": 111.73,
        "resistance_1": 112.46,
        "resistance_2": 113.73,
        "resistance_3": 114.46,
        "support_1": 110.46,
        "support_2": 109.73,
        "support_3": 107.0
      }
    },
    "XLU": {
      "name": "Utilities Select Sector SPDR Fund",
      "symbol": "XLU",
      "sector_name": "Utilities",
      "gics_code": "55",
      "description": "Electric, gas, water utilities, renewable energy",
      "current_price": 89.57,
      "daily_change": 1.1,
      "daily_change_percent": 1.24,
      "volume": 3796648,
      "day_high": 89.71,
      "day_low": 89.17,
      "day_open": 89.17,
      "52_week_high": 92.9,
      "52_week_low": 72.1,
      "distance_from_52w_high_percent": -3.58,
      "year_to_date_percent": 19.89,
      "1_month_percent": -0.92,
      "3_month_percent": 4.8,
      "6_month_percent": 13.36,
      "relative_to_sp500_1d": -0.58,
      "pivot_points": {
        "pivot_point": 88.76,
        "resistance_1": 89.25,
        "resistance_2": 90.02,
        "resistance_3": 90.51,
        "support_1": 87.99,
        "support_2": 87.5,
        "support_3": 85.76
      }
    },
    "XLRE": {
      "name": "Real Estate Select Sector SPDR Fund",
      "symbol": "XLRE",
      "sector_name": "Real Estate",
      "gics_code": "60",
      "description": "REITs, real estate management and development",
      "current_price": 40.87,
      "daily_change": 0.36,
      "daily_change_percent": 0.89,
      "volume": 1896350,
      "day_high": 40.98,
      "day_low": 40.69,
      "day_open": 40.83,
      "52_week_high": 43.71,
      "52_week_low": 36.47,
      "distance_from_52w_high_percent": -6.51,
      "year_to_date_percent": 3.79,
      "1_month_percent": -3.94,
      "3_month_percent": -2.75,
      "6_month_percent": 2.26,
      "relative_to_sp500_1d": -0.93,
      "pivot_points": {
        "pivot_point": 40.58,
        "resistance_1": 40.78,
        "resistance_2": 41.05,
        "resistance_3": 41.25,
        "support_1": 40.31,
        "support_2": 40.11,
        "support_3": 39.44
      }
    }
  },
  "sector_summary": {
    "top_performers_1d": [
      {
        "sector": "XLK",
        "return": 2.25
      },
      {
        "sector": "XLY",
        "return": 1.98
      },
      {
        "sector": "XLE",
        "return": 1.74
      }
    ],
    "bottom_performers_1d": [
      {
        "sector": "XLV",
        "return": 0.01
      },
      {
        "sector": "XLP",
        "return": 0.8
      },
      {
        "sector": "XLB",
        "return": 0.87
      }
    ],
    "sectors_beating_sp500": 2,
    "breadth_score": 18.2,
    "market_leadership": "cyclical",
    "defensive_strength": "weak"
  }
}